pykit_watch/watch/cli_replaywatch.py
robotpy_pykit_watch-1.0.0.dist-info/licenses/LICENSE
robotpy_pykit_watch-1.0.0.dist-info/METADATA
robotpy_pykit_watch-1.0.0.dist-info/WHEEL
robotpy_pykit_watch-1.0.0.dist-info/entry_points.txt
robotpy_pykit_watch-1.0.0.dist-info/top_level.txt
robotpy_pykit_watch-1.0.0.dist-info/RECORD
