Metadata-Version: 2.4
Name: robotpy-pykit-watch
Version: 1.0.0
Summary: Replay watch functionality to PyKit
Author-email: Luke Maxwell <luke@whsrobotics.org>
License-Expression: BSD-3-Clause
Project-URL: Homepage, https://github.com/1757WestwoodRobotics/PyKitWatch
Keywords: pykit,frc,robotics,logging,telemetry,replay
Requires-Python: >=3.10
License-File: LICENSE
Requires-Dist: pyfrc>=2026.0.1
Requires-Dist: watchdog>=6.0.0
Requires-Dist: wpilib>=2026.1.1
Dynamic: license-file
